mcp_ols.py
mcp_ols-0.2.2.dist-info/METADATA
mcp_ols-0.2.2.dist-info/WHEEL
mcp_ols-0.2.2.dist-info/entry_points.txt
mcp_ols-0.2.2.dist-info/licenses/LICENSE
mcp_ols-0.2.2.dist-info/RECORD
