Metadata-Version: 2.4
Name: mcp-ols
Version: 0.2.2
Summary: MCP server to add linear regression capabilities to LLMs.
License-File: LICENSE
Requires-Python: >=3.12
Requires-Dist: fastmcp>=2.9.2
Requires-Dist: fastparquet>=2024.11.0
Requires-Dist: matplotlib>=3.10.3
Requires-Dist: openpyxl>=3.1.5
Requires-Dist: pandas>=2.3.0
Requires-Dist: scipy==1.15.3
Requires-Dist: seaborn>=0.13.2
Requires-Dist: sqlalchemy>=2.0.41
Requires-Dist: statsmodels>=0.14.4
Requires-Dist: tabulate>=0.9.0
Provides-Extra: test
Requires-Dist: pytest; extra == 'test'
Requires-Dist: pytest-asyncio; extra == 'test'
